odoo/addons/account_analytic_spread_by_tag/README.rst
odoo/addons/account_analytic_spread_by_tag/__init__.py
odoo/addons/account_analytic_spread_by_tag/__manifest__.py
odoo/addons/account_analytic_spread_by_tag/i18n/account_analytic_spread_by_tag.pot
odoo/addons/account_analytic_spread_by_tag/i18n/ca_ES.po
odoo/addons/account_analytic_spread_by_tag/i18n/en_US.po
odoo/addons/account_analytic_spread_by_tag/i18n/es.po
odoo/addons/account_analytic_spread_by_tag/i18n/it.po
odoo/addons/account_analytic_spread_by_tag/models/__init__.py
odoo/addons/account_analytic_spread_by_tag/models/account_analytic_account.py
odoo/addons/account_analytic_spread_by_tag/models/account_analytic_tag.py
odoo/addons/account_analytic_spread_by_tag/models/account_move_line.py
odoo/addons/account_analytic_spread_by_tag/readme/CONFIGURE.md
odoo/addons/account_analytic_spread_by_tag/readme/CONTRIBUTORS.md
odoo/addons/account_analytic_spread_by_tag/readme/DESCRIPTION.md
odoo/addons/account_analytic_spread_by_tag/readme/ROADMAP.md
odoo/addons/account_analytic_spread_by_tag/readme/USAGE.md
odoo/addons/account_analytic_spread_by_tag/static/description/icon.png
odoo/addons/account_analytic_spread_by_tag/static/description/index.html
odoo/addons/account_analytic_spread_by_tag/static/img/image.png
odoo/addons/account_analytic_spread_by_tag/static/img/image2.png
odoo/addons/account_analytic_spread_by_tag/static/img/image3.png
odoo/addons/account_analytic_spread_by_tag/tests/__init__.py
odoo/addons/account_analytic_spread_by_tag/tests/common.py
odoo/addons/account_analytic_spread_by_tag/tests/test_account_analytic_spread.py
odoo/addons/account_analytic_spread_by_tag/views/account_analytic_account_views.xml
odoo/addons/account_analytic_spread_by_tag/views/account_analytic_tag_views.xml
odoo_addon_account_analytic_spread_by_tag-18.0.1.0.0.2.dist-info/METADATA
odoo_addon_account_analytic_spread_by_tag-18.0.1.0.0.2.dist-info/WHEEL
odoo_addon_account_analytic_spread_by_tag-18.0.1.0.0.2.dist-info/top_level.txt
odoo_addon_account_analytic_spread_by_tag-18.0.1.0.0.2.dist-info/RECORD
