Metadata-Version: 2.1
Name: odoo-addon-account_analytic_spread_by_tag
Version: 18.0.1.0.0.2
Requires-Python: >=3.10
Requires-Dist: odoo-addon-account_analytic_tag==18.0.*
Requires-Dist: odoo==18.0.*
Summary: Account Analytic Spread by Tag
Home-page: https://github.com/OCA/account-analytic
License: AGPL-3
Author: Miquel Alzanillas (APSL-Nagarro), Odoo Community Association (OCA)
Author-email: support@odoo-community.org
Classifier: Programming Language :: Python
Classifier: Framework :: Odoo
Classifier: Framework :: Odoo :: 18.0
Classifier: License :: OSI Approved :: GNU Affero General Public License v3
